wmo_sphinx_theme/__init__.py
wmo_sphinx_theme/layout.html
wmo_sphinx_theme/theme.conf
wmo_sphinx_theme/static/wmo.css
wmo_sphinx_theme-0.1.4.dist-info/LICENSE
wmo_sphinx_theme-0.1.4.dist-info/METADATA
wmo_sphinx_theme-0.1.4.dist-info/WHEEL
wmo_sphinx_theme-0.1.4.dist-info/entry_points.txt
wmo_sphinx_theme-0.1.4.dist-info/top_level.txt
wmo_sphinx_theme-0.1.4.dist-info/RECORD
