Metadata-Version: 2.1
Name: wmo-sphinx-theme
Version: 0.1.4
Summary: Sphinx theme for WMO projects
Home-page: https://github.com/wmo-im/wmo-sphinx-theme
Author: Maaike Limper
Author-email: mlimper@wmo.int
Maintainer: Maaike Limper
Maintainer-email: mlimper@wmo.int
License: Apache Software License
Keywords: wmo
Platform: all
Classifier: Development Status :: 4 - Beta
Classifier: Environment :: Console
Classifier: Intended Audience :: Developers
Classifier: Intended Audience :: Science/Research
Classifier: License :: OSI Approved :: Apache Software License
Classifier: Operating System :: OS Independent
Classifier: Topic :: Documentation
Classifier: Topic :: Software Development :: Documentation
License-File: LICENSE
